nenupytv/__init__.py
nenupytv/metadata.py
nenupytv/astro/__init__.py
nenupytv/astro/astro.py
nenupytv/calibration/__init__.py
nenupytv/calibration/calibration.py
nenupytv/calibration/lfsky.fits
nenupytv/calibration/skymodel.py
nenupytv/calibration/skymodel_old.py
nenupytv/image/__init__.py
nenupytv/image/dirty.py
nenupytv/image/filter.py
nenupytv/image/grid.py
nenupytv/image/image.py
nenupytv/image/imager.py
nenupytv/image/nearfield.py
nenupytv/image/sphmap.py
nenupytv/image/visibilities.py
nenupytv/image/visibilities_old.py
nenupytv/image/weight.py
nenupytv/instru/__init__.py
nenupytv/instru/location_miniarrays.dat
nenupytv/instru/miniarray.py
nenupytv/instru/nenufar.py
nenupytv/instru/nenufar_inst.py
nenupytv/instru/radioarray.py
nenupytv/read/__init__.py
nenupytv/read/crosslets.py
nenupytv/read/xst.py
nenupytv/response/__init__.py
nenupytv/response/beam.py
nenupytv/response/psf.py
nenupytv/uvw/__init__.py
nenupytv/uvw/test_uvw.py
nenupytv/uvw/uvw.py
nenupytv/uvw/uvw_old.py
nenupytv-1.2.0.data/scripts/nenufartv
nenupytv-1.2.0.data/scripts/nenufartv_mp
nenupytv-1.2.0.dist-info/LICENSE
nenupytv-1.2.0.dist-info/METADATA
nenupytv-1.2.0.dist-info/WHEEL
nenupytv-1.2.0.dist-info/top_level.txt
nenupytv-1.2.0.dist-info/RECORD
