Metadata-Version: 2.1
Name: nenupytv
Version: 1.2.0
Summary: NenuFAR-TV Python package
Home-page: https://github.com/AlanLoh/nenupy-tv.git
Author: Alan Loh
Author-email: alan.loh@obspm.fr
License: MIT
Platform: UNKNOWN
Classifier: Programming Language :: Python :: 3
Requires-Python: >=3.5
Requires-Dist: numpy
Requires-Dist: astropy
